flask_2_ui5_py/__init__.py
flask_2_ui5_py/json_util.py
flask_2_ui5_py/message_util.py
flask_2_ui5_py-0.0.1.dist-info/METADATA
flask_2_ui5_py-0.0.1.dist-info/WHEEL
flask_2_ui5_py-0.0.1.dist-info/top_level.txt
flask_2_ui5_py-0.0.1.dist-info/RECORD
